Registers/sync_loadclearreg.v
module sync_loadclearreg(
    input load, clear, clk,
    input [7:0]D,
    output reg [7:0]Qout
    );

    always @(posedge clk)begin
        if (load)begin //Load hai hamara active high
            Qout <= D;
        end else if (~clear)begin //clear hai hamara active low
            Qout <= 8'b0;
        end
    end
endmodule


//Ye wala register ek step upar liya hai
//Load: Jab ye on hoga tab hi register new values lega
//Jab na hi load hai na hi clear tab register hold me chala jaega
//Jab clear on hai to register ki previous memory clear ho jaegi

Registers/tb_sync_loadclearreg.v
`timescale 1ns/1ps

module tb_sync_loadclearreg();
    reg clear;
    reg load;
    reg clk;
    reg [7:0]D;
    wire [7:0]Qout;

    sync_loadclearreg register(
        .clear(clear),
        .load(load),
        .clk(clk),
        .D(D),
        .Qout(Qout)
    );

    initial begin
        clear = 1'b1;
        load = 1'b0;
        clk = 1'b0;
        #5;
    end

    always begin
        clk = ~clk;
        #2;
    end

    initial begin
        $dumpfile("improvedregwaveform.vcd");
        $dumpvars(0, tb_sync_loadclearreg);

        #5;
        load = 1'b1;
        #5;
        $display("LOAD = %d | CLEAR = %d | D = %d | Qout = %d |", load, clear, D, Qout);

        D = 8'd0;
        #5;
        $display("LOAD = %d | CLEAR = %d | D = %d | Qout = %d |", load, clear, D, Qout);

        #5;
        D = 8'd255;
        #5;
        $display("LOAD = %d | CLEAR = %d | D = %d | Qout = %d |", load, clear, D, Qout);

        clear = 1'b0;
        #5;
        $display("LOAD = %d | CLEAR = %d | D = %d | Qout = %d |", load, clear, D, Qout);

        D = 8'd128;
        #5;
        $display("LOAD = %d | CLEAR = %d | D = %d | Qout = %d |", load, clear, D, Qout);

        clear = 1'b1;
        #5;
        $display("LOAD = %d | CLEAR = %d | D = %d | Qout = %d |", load, clear, D, Qout);

        load = 1'b0;
        #5;
        $display("LOAD = %d | CLEAR = %d | D = %d | Qout = %d |", load, clear, D, Qout);

        D = 8'd69;
        #5;
        $display("LOAD = %d | CLEAR = %d | D = %d | Qout = %d |", load, clear, D, Qout);

        load = 1'b0;
        clear = 1'b1;
        #5
        $display("LOAD = %d | CLEAR = %d | D = %d | Qout = %d |", load, clear, D, Qout);
        $finish;
    end
endmodule

improvedregwaveform.vcd
$date
	Sat Aug 30 12:55:33 2025
$end
$version
	Icarus Verilog
$end
$timescale
	1ps
$end
$scope module tb_sync_loadclearreg $end
$var wire 8 ! Qout [7:0] $end
$var reg 8 " D [7:0] $end
$var reg 1 # clear $end
$var reg 1 $ clk $end
$var reg 1 % load $end
$scope module register $end
$var wire 8 & D [7:0] $end
$var wire 1 # clear $end
$var wire 1 $ clk $end
$var wire 1 % load $end
$var reg 8 ' Qout [7:0] $end
$upscope $end
$upscope $end
$enddefinitions $end
$comment Show the parameter values. $end
$dumpall
$end
#0
$dumpvars
bx '
bx &
0%
1$
1#
bx "
bx !
$end
#2000
0$
#4000
1$
#5000
1%
#6000
0$
#8000
1$
#10000
0$
b0 "
b0 &
#12000
b0 !
b0 '
1$
#14000
0$
#16000
1$
#18000
0$
#20000
b11111111 !
b11111111 '
1$
b11111111 "
b11111111 &
#22000
0$
#24000
1$
#25000
0#
#26000
0$
#28000
1$
#30000
0$
b10000000 "
b10000000 &
#32000
b10000000 !
b10000000 '
1$
#34000
0$
#35000
1#
#36000
1$
#38000
0$
#40000
1$
0%
#42000
0$
#44000
1$
#45000
b1000101 "
b1000101 &
