ffsandlatches/jk_ff.v
module jk_ff(
    input clk, j, k,
    output reg q
    );
    initial begin
        q = 1'b0;
    end

    always @(posedge clk)begin
        if (j == 1'b0 && k == 1'b0)begin
            q <= q;
        end else if (j == 1'b0 && k == 1'b1)begin
            q <= 1'b0;
        end else if (j == 1'b1 && k == 1'b0)begin
            q <= 1'b1;
        end else begin
            q <= ~q;
        end
    end
endmodule

ffsandlatches/tb_jk_ff.v
`timescale 1ns/1ps

module tb_jk_ff();
    reg j;
    reg k;
    reg clk;
    wire q;

    jk_ff uut (
        .j(j),
        .k(k),
        .clk(clk),
        .q(q)
    );

    initial begin
        j = 1'b0;
        k = 1'b0;
        clk = 1'b0;
        #2;
    end

    always begin
        clk = ~clk;
        #2;
    end

    initial begin
        $dumpfile("jkwaveform.vcd");
        $dumpvars(0, tb_jk_ff);

        j = 1'b0;
        k = 1'b0;
        #5;
        $display("J = %b K = %b | Q = %b", j, k, q);

        k = 1'b1;
        #5;
        $display("J = %b K = %b | Q = %b", j, k, q);

        k = 1'b0;
        #5;
        $display("J = %b K = %b | Q = %b", j, k, q);

        j = 1'b1;
        #5;
        $display("J = %b K = %b | Q = %b", j, k, q);

        j = 1'b0;
        #5;
        $display("J = %b K = %b | Q = %b", j, k, q);

        j = 1'b1;
        k = 1'b1;
        #5;
        $display("J = %b K = %b | Q = %b", j, k, q);

        j = 1'b0;
        k = 1'b0;
        #5;
        $display("J = %b K = %b | Q = %b", j, k, q);
        $finish;
    end
endmodule

jkwaveform.vcd
$date
	Wed Aug 27 17:09:48 2025
$end
$version
	Icarus Verilog
$end
$timescale
	1ps
$end
$scope module tb_jk_ff $end
$var wire 1 ! q $end
$var reg 1 " clk $end
$var reg 1 # j $end
$var reg 1 $ k $end
$scope module uut $end
$var wire 1 " clk $end
$var wire 1 # j $end
$var wire 1 $ k $end
$var reg 1 ! q $end
$upscope $end
$upscope $end
$enddefinitions $end
$comment Show the parameter values. $end
$dumpall
$end
#0
$dumpvars
0$
0#
1"
0!
$end
#2000
0"
#4000
1"
#5000
1$
#6000
0"
#8000
1"
#10000
0"
0$
#12000
1"
#14000
0"
#15000
1#
#16000
1!
1"
#18000
0"
#20000
1"
0#
#22000
0"
#24000
1"
#25000
1$
1#
#26000
0"
#28000
0!
1"
#30000
0"
0$
0#
